run.py
test.py
resetTolkien/__init__.py
resetTolkien/__main__.py
resetTolkien/cli.py
resetTolkien/constants.py
resetTolkien/format.py
resetTolkien/hashes.py
resetTolkien/resetTolkien.py
resetTolkien/utils.py
resetTolkien/config/default.yml
resetTolkien/config/default2.yml
reset_tolkien-1.3.4.dist-info/LICENSE
reset_tolkien-1.3.4.dist-info/METADATA
reset_tolkien-1.3.4.dist-info/WHEEL
reset_tolkien-1.3.4.dist-info/entry_points.txt
reset_tolkien-1.3.4.dist-info/top_level.txt
reset_tolkien-1.3.4.dist-info/RECORD
