Metadata-Version: 2.1
Name: reset-tolkien
Version: 1.3.4
Summary: Unsecure time-based secret exploitation and Sandwich attack implementation.
Author-email: Tom CHAMBARETAUD <contact@aeth.cc>
Maintainer-email: Tom CHAMBARETAUD <contact@aeth.cc>
License: MIT License
Project-URL: Homepage, https://github.com/AethliosIK/reset-tolkien
Project-URL: Repository, https://github.com/AethliosIK/reset-tolkien
Project-URL: Issues, https://github.com/AethliosIK/reset-tolkien/issues
Project-URL: Changelog, https://github.com/AethliosIK/reset-tolkien/blob/master/CHANGELOG.md
Keywords: security,secret,reset,token,tolkien
Classifier: Development Status :: 5 - Production/Stable
Classifier: Environment :: Console
Classifier: Intended Audience :: Information Technology
Classifier: Intended Audience :: System Administrators
Classifier: Intended Audience :: Developers
Classifier: License :: OSI Approved :: MIT License
Classifier: Natural Language :: English
Classifier: Programming Language :: Python
Classifier: Programming Language :: Python :: 3
Classifier: Programming Language :: Python :: 3 :: Only
Classifier: Programming Language :: Python :: 3.10
Classifier: Topic :: Security
Classifier: Topic :: Security :: Cryptography
Classifier: Topic :: Software Development :: Debuggers
Classifier: Topic :: System :: Systems Administration
Classifier: Topic :: Software Development :: Testing
Classifier: Topic :: Utilities
Classifier: Typing :: Typed
Requires-Python: >=3.10
License-File: LICENSE
Requires-Dist: dateparser==1.1.8
Requires-Dist: hi-dateinfer==0.4.6
Requires-Dist: packaging==23.2
Requires-Dist: python-dateutil==2.9.0.post0
Requires-Dist: pytz==2024.1
Requires-Dist: PyYAML==6.0.1
Requires-Dist: regex==2023.12.25
Requires-Dist: shortuuid==1.0.11
Requires-Dist: six==1.16.0
Requires-Dist: typing_extensions==4.10.0
Requires-Dist: tzlocal==5.2
Requires-Dist: tqdm==4.66.5
Provides-Extra: dev
Requires-Dist: setuptools==68.2.0; extra == "dev"
Requires-Dist: build==1.0.3; extra == "dev"
Requires-Dist: twine==4.0.2; extra == "dev"
